{
"type": "FeatureCollection",
"name": "Tibicina_steveni",
"features": [
{"type": "Feature", "properties": {"ID": "d7eb3629-f8cf-4313-bf03-310adacd5b48"},"geometry": {"coordinates": [4.73136,45.58212],"type": "Point"},"id": "d7eb3629-f8cf-4313-bf03-310adacd5b48"},
{"type": "Feature", "properties": {"ID": "66fad24c-4510-4bf2-b92f-7744250d6836"},"geometry": {"coordinates": [2.83911,44.0857],"type": "Point"},"id": "66fad24c-4510-4bf2-b92f-7744250d6836"},
{"type": "Feature", "properties": {"ID": "8c95a6c7-ec9b-494e-9a3c-5686df385351"},"geometry": {"coordinates": [1.78505,44.04806],"type": "Point"},"id": "8c95a6c7-ec9b-494e-9a3c-5686df385351"},
{"type": "Feature", "properties": {"ID": "7c205128-f28a-4ac9-96fe-daa6839e05e5"},"geometry": {"coordinates": [4.73136,45.58212],"type": "Point"},"id": "7c205128-f28a-4ac9-96fe-daa6839e05e5"},
{"type": "Feature", "properties": {"ID": "0f0e6799-7f9d-4e18-98eb-b0909f5aa813"},"geometry": {"coordinates": [4.09583,44.251],"type": "Point"},"id": "0f0e6799-7f9d-4e18-98eb-b0909f5aa813"},
{"type": "Feature", "properties": {"ID": "f87cc08e-e338-4ec8-ae54-4c602ec76054"},"geometry": {"coordinates": [4.73136,45.58212],"type": "Point"},"id": "f87cc08e-e338-4ec8-ae54-4c602ec76054"},
{"type": "Feature", "properties": {"ID": "fcbdd22a-8921-40bc-a1e5-856606c51572"},"geometry": {"coordinates": [4.73136,45.58212],"type": "Point"},"id": "fcbdd22a-8921-40bc-a1e5-856606c51572"},
{"type": "Feature", "properties": {"ID": "ca5e9d4f-0b8a-4843-8442-77e4e34f6b35"},"geometry": {"coordinates": [4.73136,45.58212],"type": "Point"},"id": "ca5e9d4f-0b8a-4843-8442-77e4e34f6b35"},
{"type": "Feature", "properties": {"ID": "fee657c3-20f1-4f1d-b2f1-0b7bf8220831"},"geometry": {"coordinates": [4.60971,45.52238],"type": "Point"},"id": "fee657c3-20f1-4f1d-b2f1-0b7bf8220831"},
{"type": "Feature", "properties": {"ID": "b39e4a5b-c15b-4164-a75e-18ba813ca88b"},"geometry": {"coordinates": [4.73136,45.58212],"type": "Point"},"id": "b39e4a5b-c15b-4164-a75e-18ba813ca88b"},
{"type": "Feature", "properties": {"ID": "9fd44fd9-c1c4-4cd4-a903-bae0749cfe21"},"geometry": {"coordinates": [4.04335,44.22863],"type": "Point"},"id": "9fd44fd9-c1c4-4cd4-a903-bae0749cfe21"},
{"type": "Feature", "properties": {"ID": "065008c3-166f-4b53-b825-899d0b69b575"},"geometry": {"coordinates": [4.0364,44.2284],"type": "Point"},"id": "065008c3-166f-4b53-b825-899d0b69b575"},
{"type": "Feature", "properties": {"ID": "c4b01cfa-2063-459a-ac4d-788b9f81e054"},"geometry": {"coordinates": [2.81142,44.07183],"type": "Point"},"id": "c4b01cfa-2063-459a-ac4d-788b9f81e054"},
{"type": "Feature", "properties": {"ID": "b4680542-3861-421d-b1cc-e066696704ef"},"geometry": {"coordinates": [2.72611,43.98122],"type": "Point"},"id": "b4680542-3861-421d-b1cc-e066696704ef"},
{"type": "Feature", "properties": {"ID": "1f18701f-3126-4803-9c86-9b6da9e6da15"},"geometry": {"coordinates": [1.7554,44.05019],"type": "Point"},"id": "1f18701f-3126-4803-9c86-9b6da9e6da15"},
{"type": "Feature", "properties": {"ID": "8fb99ce5-4887-48b3-b531-e705863a8f88"},"geometry": {"coordinates": [2.88678,44.04743],"type": "Point"},"id": "8fb99ce5-4887-48b3-b531-e705863a8f88"},
{"type": "Feature", "properties": {"ID": "d1f91f6a-48f3-44d3-8130-8d3d25f7293c"},"geometry": {"coordinates": [2.71311,44.01794],"type": "Point"},"id": "d1f91f6a-48f3-44d3-8130-8d3d25f7293c"},
{"type": "Feature", "properties": {"ID": "01c9dcd7-4828-4dfe-b329-6396584946b7"},"geometry": {"coordinates": [2.71311,44.01794],"type": "Point"},"id": "01c9dcd7-4828-4dfe-b329-6396584946b7"},
{"type": "Feature", "properties": {"ID": "ede4ca9e-019c-42f1-bd69-0797c0cdea6b"},"geometry": {"coordinates": [1.71171,44.01075],"type": "Point"},"id": "ede4ca9e-019c-42f1-bd69-0797c0cdea6b"},
{"type": "Feature", "properties": {"ID": "f0844f23-5f49-4f9e-a2ee-7fafdbb5abb2"},"geometry": {"coordinates": [2.88678,44.04743],"type": "Point"},"id": "f0844f23-5f49-4f9e-a2ee-7fafdbb5abb2"},
{"type": "Feature", "properties": {"ID": "f15a690f-c099-492a-ad6d-fdd149b545b4"},"geometry": {"coordinates": [1.73053,43.95127],"type": "Point"},"id": "f15a690f-c099-492a-ad6d-fdd149b545b4"},
{"type": "Feature", "properties": {"ID": "94ee5b02-11c9-4f9d-b7e6-d656e6e8ff73"},"geometry": {"coordinates": [2.74401,44.04308],"type": "Point"},"id": "94ee5b02-11c9-4f9d-b7e6-d656e6e8ff73"},
{"type": "Feature", "properties": {"ID": "558ff585-afa4-4c9e-ac33-574a955f423e"},"geometry": {"coordinates": [1.75788,44.04913],"type": "Point"},"id": "558ff585-afa4-4c9e-ac33-574a955f423e"},
{"type": "Feature", "properties": {"ID": "11f87fcd-df24-47ea-b004-86457e9995ba"},"geometry": {"coordinates": [2.89441,44.05138],"type": "Point"},"id": "11f87fcd-df24-47ea-b004-86457e9995ba"},
{"type": "Feature", "properties": {"ID": "94a86a5b-0e45-418f-abdf-3141a52f7802"},"geometry": {"coordinates": [2.87017,44.0574],"type": "Point"},"id": "94a86a5b-0e45-418f-abdf-3141a52f7802"}
]}
