{
"type": "FeatureCollection",
"name": "Dimissalna_dimissa",
"features": [
{"type": "Feature", "properties": {"ID": "169005235"},"geometry": {"coordinates": [6.3225198537,43.4782388354],"type": "Point"},"id": "169005235"},
{"type": "Feature", "properties": {"ID": "175348712"},"geometry": {"coordinates": [4.0240400657,44.2692179685],"type": "Point"},"id": "175348712"},
{"type": "Feature", "properties": {"ID": "228860611"},"geometry": {"coordinates": [4.4403842015,44.3513999863],"type": "Point"},"id": "228860611"},
{"type": "Feature", "properties": {"ID": "86682671"},"geometry": {"coordinates": [4.52473195,44.25809677],"type": "Point"},"id": "86682671"}
]}
