{
"type": "FeatureCollection",
"name": "Tibicina_steveni",
"features": [
{"type": "Feature", "properties": {"ID": "4171167913"},"geometry": {"coordinates": [3.995502,44.228323],"type": "Point"},"id": "4171167913"},
{"type": "Feature", "properties": {"ID": "4145328643"},"geometry": {"coordinates": [3.995534,44.228227],"type": "Point"},"id": "4145328643"},
{"type": "Feature", "properties": {"ID": "4137601023"},"geometry": {"coordinates": [3.99555,44.228303],"type": "Point"},"id": "4137601023"},
{"type": "Feature", "properties": {"ID": "4145354978"},"geometry": {"coordinates": [3.856974,44.044654],"type": "Point"},"id": "4145354978"},
{"type": "Feature", "properties": {"ID": "4054842430"},"geometry": {"coordinates": [2.86165,43.51611],"type": "Point"},"id": "4054842430"},
{"type": "Feature", "properties": {"ID": "4149169454"},"geometry": {"coordinates": [4.73136,45.58212],"type": "Point"},"id": "4149169454"},
{"type": "Feature", "properties": {"ID": "4149207709"},"geometry": {"coordinates": [4.73136,45.58212],"type": "Point"},"id": "4149207709"},
{"type": "Feature", "properties": {"ID": "4149143455"},"geometry": {"coordinates": [4.73136,45.58212],"type": "Point"},"id": "4149143455"},
{"type": "Feature", "properties": {"ID": "4149221726"},"geometry": {"coordinates": [4.73136,45.58212],"type": "Point"},"id": "4149221726"},
{"type": "Feature", "properties": {"ID": "4149161513"},"geometry": {"coordinates": [4.73136,45.58212],"type": "Point"},"id": "4149161513"},
{"type": "Feature", "properties": {"ID": "4149148054"},"geometry": {"coordinates": [4.73136,45.58212],"type": "Point"},"id": "4149148054"},
{"type": "Feature", "properties": {"ID": "4054892439"},"geometry": {"coordinates": [2.832296,43.522513],"type": "Point"},"id": "4054892439"},
{"type": "Feature", "properties": {"ID": "4047041264"},"geometry": {"coordinates": [2.83911,44.0857],"type": "Point"},"id": "4047041264"},
{"type": "Feature", "properties": {"ID": "3944399374"},"geometry": {"coordinates": [2.87017,44.0574],"type": "Point"},"id": "3944399374"},
{"type": "Feature", "properties": {"ID": "3491654688"},"geometry": {"coordinates": [1.75788,44.04913],"type": "Point"},"id": "3491654688"},
{"type": "Feature", "properties": {"ID": "3491654780"},"geometry": {"coordinates": [1.7554,44.05019],"type": "Point"},"id": "3491654780"},
{"type": "Feature", "properties": {"ID": "3495732343"},"geometry": {"coordinates": [1.71171,44.01075],"type": "Point"},"id": "3495732343"},
{"type": "Feature", "properties": {"ID": "3496146289"},"geometry": {"coordinates": [1.73053,43.95127],"type": "Point"},"id": "3496146289"},
{"type": "Feature", "properties": {"ID": "3496201938"},"geometry": {"coordinates": [2.88678,44.04743],"type": "Point"},"id": "3496201938"},
{"type": "Feature", "properties": {"ID": "3939497301"},"geometry": {"coordinates": [4.0364,44.2284],"type": "Point"},"id": "3939497301"},
{"type": "Feature", "properties": {"ID": "3939497347"},"geometry": {"coordinates": [4.04335,44.22863],"type": "Point"},"id": "3939497347"},
{"type": "Feature", "properties": {"ID": "2475576675"},"geometry": {"coordinates": [4.60971,45.52238],"type": "Point"},"id": "2475576675"},
{"type": "Feature", "properties": {"ID": "3495877386"},"geometry": {"coordinates": [2.74401,44.04308],"type": "Point"},"id": "3495877386"},
{"type": "Feature", "properties": {"ID": "3495748992"},"geometry": {"coordinates": [2.72611,43.98122],"type": "Point"},"id": "3495748992"},
{"type": "Feature", "properties": {"ID": "3495752633"},"geometry": {"coordinates": [2.89441,44.05138],"type": "Point"},"id": "3495752633"},
{"type": "Feature", "properties": {"ID": "3495767598"},"geometry": {"coordinates": [2.81142,44.07183],"type": "Point"},"id": "3495767598"},
{"type": "Feature", "properties": {"ID": "3496058071"},"geometry": {"coordinates": [2.88678,44.04743],"type": "Point"},"id": "3496058071"},
{"type": "Feature", "properties": {"ID": "3496140226"},"geometry": {"coordinates": [2.71311,44.01794],"type": "Point"},"id": "3496140226"},
{"type": "Feature" "properties": {"ID": "3495868721"}"geometry": {"coordinates": [2.7131144.01794]"type": "Point"}"id": "3495868721"}
]}
